cads_toolbox/__init__.py
cads_toolbox/_inputs_transform.py
cads_toolbox/catalogue.py
cads_toolbox/config.py
cads_toolbox/version.py
cads_toolbox/analysis/__init__.py
cads_toolbox-0.0.2b0.dist-info/LICENSE
cads_toolbox-0.0.2b0.dist-info/METADATA
cads_toolbox-0.0.2b0.dist-info/WHEEL
cads_toolbox-0.0.2b0.dist-info/top_level.txt
cads_toolbox-0.0.2b0.dist-info/RECORD
