Metadata-Version: 2.1
Name: cads-toolbox
Version: 0.0.2b0
Summary: CADS Toolbox library provides an entry point to the CADS data and software
License: Apache License 2.0
Classifier: Development Status :: 2 - Pre-Alpha
Classifier: Intended Audience :: Science/Research
Classifier: License :: OSI Approved :: Apache Software License
Classifier: Operating System :: OS Independent
Classifier: Programming Language :: Python
Classifier: Programming Language :: Python :: 3
Classifier: Programming Language :: Python :: 3.10
Classifier: Programming Language :: Python :: 3.9
Classifier: Programming Language :: Python :: 3.8
Classifier: Topic :: Scientific/Engineering
License-File: LICENSE
Requires-Dist: cacholote
Requires-Dist: cdsapi
Requires-Dist: coucal
Requires-Dist: emohawk (>=0.0.3b1)
Requires-Dist: fsspec
